setup.py
solaraund/__init__.py
solaraund/solaraund.py
solaraund.egg-info/PKG-INFO
solaraund.egg-info/SOURCES.txt
solaraund.egg-info/dependency_links.txt
solaraund.egg-info/top_level.txt