Metadata-Version: 2.1
Name: solaraund
Version: 0.1
Summary: cantdoitanymorehaahahaaha
